claude_monitor/__init__.py
claude_monitor/__main__.py
claude_monitor/_version.py
claude_monitor/error_handling.py
claude_monitor/cli/__init__.py
claude_monitor/cli/bootstrap.py
claude_monitor/cli/main.py
claude_monitor/core/__init__.py
claude_monitor/core/calculations.py
claude_monitor/core/data_processors.py
claude_monitor/core/models.py
claude_monitor/core/p90_calculator.py
claude_monitor/core/plans.py
claude_monitor/core/pricing.py
claude_monitor/core/settings.py
claude_monitor/data/__init__.py
claude_monitor/data/aggregator.py
claude_monitor/data/analysis.py
claude_monitor/data/analyzer.py
claude_monitor/data/reader.py
claude_monitor/monitoring/__init__.py
claude_monitor/monitoring/data_manager.py
claude_monitor/monitoring/orchestrator.py
claude_monitor/monitoring/session_monitor.py
claude_monitor/terminal/__init__.py
claude_monitor/terminal/manager.py
claude_monitor/terminal/themes.py
claude_monitor/ui/__init__.py
claude_monitor/ui/components.py
claude_monitor/ui/display_controller.py
claude_monitor/ui/layouts.py
claude_monitor/ui/progress_bars.py
claude_monitor/ui/session_display.py
claude_monitor/ui/table_views.py
claude_monitor/utils/__init__.py
claude_monitor/utils/formatting.py
claude_monitor/utils/model_utils.py
claude_monitor/utils/notifications.py
claude_monitor/utils/time_utils.py
claude_monitor/utils/timezone.py
claude_monitor-3.1.0.dist-info/licenses/LICENSE
claude_monitor-3.1.0.dist-info/METADATA
claude_monitor-3.1.0.dist-info/WHEEL
claude_monitor-3.1.0.dist-info/entry_points.txt
claude_monitor-3.1.0.dist-info/top_level.txt
claude_monitor-3.1.0.dist-info/RECORD
