Metadata-Version: 2.4
Name: claude-monitor
Version: 3.1.0
Summary: A real-time terminal monitoring tool for Claude Code token usage with advanced analytics and Rich UI
Author-email: Maciek <maciek@roboblog.eu>
Maintainer-email: Maciek <maciek@roboblog.eu>
License: MIT
Project-URL: homepage, https://github.com/Maciek-roboblog/Claude-Code-Usage-Monitor
Project-URL: repository, https://github.com/Maciek-roboblog/Claude-Code-Usage-Monitor.git
Project-URL: documentation, https://github.com/Maciek-roboblog/Claude-Code-Usage-Monitor#readme
Project-URL: issues, https://github.com/Maciek-roboblog/Claude-Code-Usage-Monitor/issues
Project-URL: changelog, https://github.com/Maciek-roboblog/Claude-Code-Usage-Monitor/blob/main/CHANGELOG.md
Project-URL: Release Notes, https://github.com/Maciek-roboblog/Claude-Code-Usage-Monitor/releases
Project-URL: Discussions, https://github.com/Maciek-roboblog/Claude-Code-Usage-Monitor/discussions
Keywords: ai,analytics,claude,dashboard,developer-tools,monitoring,rich,terminal,token,usage
Classifier: Development Status :: 5 - Production/Stable
Classifier: Environment :: Console
Classifier: Environment :: Console :: Curses
Classifier: Intended Audience :: Developers
Classifier: Topic :: Software Development :: Debuggers
Classifier: Topic :: Software Development :: Libraries :: Python Modules
Classifier: Topic :: System :: Monitoring
Classifier: Topic :: Terminals
Classifier: Topic :: Utilities
Classifier: Programming Language :: Python :: 3
Classifier: Programming Language :: Python :: 3 :: Only
Classifier: License :: OSI Approved :: MIT License
Classifier: Operating System :: OS Independent
Classifier: Operating System :: POSIX :: Linux
Classifier: Operating System :: MacOS
Classifier: Typing :: Typed
Requires-Python: >=3.9
License-File: LICENSE
Requires-Dist: numpy>=1.21.0
Requires-Dist: pydantic>=2.0.0
Requires-Dist: pydantic-settings>=2.0.0
Requires-Dist: pyyaml>=6.0
Requires-Dist: pytz>=2023.3
Requires-Dist: rich>=13.7.0
Requires-Dist: tomli>=1.2.0; python_version < "3.11"
Requires-Dist: tzdata; sys_platform == "win32"
Provides-Extra: dev
Requires-Dist: black>=24.0.0; extra == "dev"
Requires-Dist: isort>=5.13.0; extra == "dev"
Requires-Dist: mypy>=1.13.0; extra == "dev"
Requires-Dist: pre-commit>=4.0.0; extra == "dev"
Requires-Dist: pytest>=8.0.0; extra == "dev"
Requires-Dist: pytest-asyncio>=0.24.0; extra == "dev"
Requires-Dist: pytest-benchmark>=4.0.0; extra == "dev"
Requires-Dist: pytest-cov>=6.0.0; extra == "dev"
Requires-Dist: pytest-mock>=3.14.0; extra == "dev"
Requires-Dist: pytest-xdist>=3.6.0; extra == "dev"
Requires-Dist: ruff>=0.12.0; extra == "dev"
Requires-Dist: build>=0.10.0; extra == "dev"
Requires-Dist: twine>=4.0.0; extra == "dev"
Provides-Extra: test
Requires-Dist: pytest>=8.0.0; extra == "test"
Requires-Dist: pytest-cov>=6.0.0; extra == "test"
Requires-Dist: pytest-mock>=3.14.0; extra == "test"
Requires-Dist: pytest-asyncio>=0.24.0; extra == "test"
Requires-Dist: pytest-benchmark>=4.0.0; extra == "test"
Dynamic: license-file
